worldcraft_sim/__init__.py
worldcraft_sim/main.py
worldcraft_sim/prompts.py
worldcraft_sim-2025.12.20202326.dist-info/METADATA
worldcraft_sim-2025.12.20202326.dist-info/WHEEL
worldcraft_sim-2025.12.20202326.dist-info/top_level.txt
worldcraft_sim-2025.12.20202326.dist-info/RECORD
