Metadata-Version: 2.4
Name: worldcraft-sim
Version: 2025.12.20202326
Summary: A new package lets users type plain text descriptions of imaginary worlds—defining rules, ecosystems, and events—and, using LLM7 and llmatch-messages, returns a structured, step‑by‑step simulation nar
Author-email: worldcraft-sim <hi@eugene.plus>
License: MIT
Project-URL: Homepage, https://github.com/chigwell/worldcraft-sim
Requires-Python: >=3.9
Requires-Dist: langchain-llm7>=0.0.0
Requires-Dist: llmatch-messages>=0.0.0
Requires-Dist: langchain-core>=0.3.0
